d2b_sidecarless_nii.py
d2b_sidecarless_nii-1.0.0.dist-info/entry_points.txt
d2b_sidecarless_nii-1.0.0.dist-info/WHEEL
d2b_sidecarless_nii-1.0.0.dist-info/METADATA
d2b_sidecarless_nii-1.0.0.dist-info/RECORD
